blueutil_tui/__init__.py
blueutil_tui/app.py
blueutil_tui/constants.py
blueutil_tui/utils.py
blueutil_tui/widgets.py
blueutil_tui-0.2.4.dist-info/METADATA
blueutil_tui-0.2.4.dist-info/WHEEL
blueutil_tui-0.2.4.dist-info/entry_points.txt
blueutil_tui-0.2.4.dist-info/RECORD
