Metadata-Version: 2.4
Name: blueutil-tui
Version: 0.2.4
Summary: minimal tui to interact with bluetooth devices via blueutil on Mac
Project-URL: Repository, https://github.com/Zaloog/blueutil-tui
Project-URL: Changelog, https://github.com/Zaloog/blueutil-tui/blob/main/CHANGELOG.md
Author-email: Zaloog <gramslars@gmail.com>
License: MIT
Keywords: bluetooth,blueutil,mac,python,textual,tui
Classifier: Development Status :: 3 - Alpha
Classifier: Environment :: MacOS X
Classifier: License :: OSI Approved :: MIT License
Classifier: Operating System :: MacOS
Classifier: Programming Language :: Python
Classifier: Programming Language :: Python :: 3 :: Only
Classifier: Programming Language :: Python :: 3.10
Classifier: Programming Language :: Python :: 3.11
Classifier: Programming Language :: Python :: 3.12
Classifier: Programming Language :: Python :: 3.13
Requires-Python: >=3.10
Requires-Dist: textual>=2.0.0
